hwetests/__init__.py
hwetests/asta.py
hwetests/umat.py
hwetests/umat_with_uncertainty.py
hwetests/tests/__init__.py
hwetests/tests/dataloader.py
hwetests/tests/utils.py
hwetests/tests/data/ambiguous_data.csv
hwetests/tests/data/unambiguous_data.csv
hwetests/tests/scripts/__init__.py
hwetests/tests/scripts/asta_test.py
hwetests/tests/scripts/umat_test.py
hwetests/tests/scripts/umat_with_sampling_test.py
hwetests/tests/scripts/utils_test.py
hwetests-1.0.0.dist-info/LICENSE.txt
hwetests-1.0.0.dist-info/METADATA
hwetests-1.0.0.dist-info/WHEEL
hwetests-1.0.0.dist-info/top_level.txt
hwetests-1.0.0.dist-info/RECORD
