Metadata-Version: 2.1
Name: hwetests
Version: 1.0.0
Summary: A python package containing two statistical tests for HWE testing: Gibbs Sampling tests and a modified Chi Squared tests that handles ambiguity
Home-page: https://github.com/louzounlab/HWE_Tests
Author: Or Shkuri
Author-email: orshkuri2000@gmail.com
Classifier: Programming Language :: Python :: 3
Classifier: License :: OSI Approved :: MIT License
Classifier: Operating System :: OS Independent
Requires-Python: >=3.6
License-File: LICENSE.txt
Requires-Dist: numpy >=1.21.2
Requires-Dist: scipy >=1.7.1
Requires-Dist: matplotlib >=3.4.3
Requires-Dist: seaborn >=0.11.2
